base.py
extract/__init__.py
extract/json_extractor.py
load/__init__.py
load/sftp_loader.py
parsing/__init__.py
parsing/chamber_parser.py
parsing/notar_parser.py
parsing/parserManager.py
parsing/person_parser.py
parsing/relationships_parser.py
transform/__init__.py
transform/address_normalizer.py
transform/birthnameExtractor.py
transform/cleaning.py
transform/combine_gender.py
transform/date_transformer.py
transform/gender_parsing_trasnformer.py
transform/geo_transfromer.py
transform/hash_generator.py
transform/id_generator.py
transform/language_transformer.py
transform/name_transformer.py
transform/phone_normalizer.py
transform/transform_pipeline.py
transform/url_transformer.py
update/__init__.py
update/loader.py
update/updater.py
notar_pipeline-0.1.5.dist-info/METADATA
notar_pipeline-0.1.5.dist-info/WHEEL
notar_pipeline-0.1.5.dist-info/top_level.txt
notar_pipeline-0.1.5.dist-info/RECORD
