Metadata-Version: 2.4
Name: notar_pipeline
Version: 0.1.5
Summary: Modular ETL logic for Alteryx
Author-email: Youssef <youssefaferdou90@gmail.com>
Requires-Dist: pandas
Requires-Dist: python-dotenv
